nineeq/__init__.py
nineeq/cli.py
nineeq/config.py
nineeq/detector.py
nineeq/generator.py
nineeq/visualizer.py
9eq-0.1.0.dist-info/LICENSE
9eq-0.1.0.dist-info/METADATA
9eq-0.1.0.dist-info/WHEEL
9eq-0.1.0.dist-info/entry_points.txt
9eq-0.1.0.dist-info/top_level.txt
9eq-0.1.0.dist-info/RECORD
