Metadata-Version: 2.1
Name: 9eq
Version: 0.1.0
Summary: A real-time visualizer for the 9 nineeq frequencies
Home-page: https://github.com/clxrityy/9eq
Author: MJ Anglin
Author-email: MJ Anglin <contact@mjanglin.com>
License: MIT
Project-URL: Bug Tracker, https://github.com/clxrityy/9eq/issues
Project-URL: Homepage, https://github.com/clxrityy/9eq
Project-URL: Repository, https://github.com/clxrityy/9eq
Keywords: audio,visualization,nineeq,frequency,analysis
Classifier: Development Status :: 3 - Alpha
Classifier: Intended Audience :: Developers
Classifier: License :: OSI Approved :: MIT License
Classifier: Programming Language :: Python :: 3
Classifier: Programming Language :: Python :: 3.8
Classifier: Programming Language :: Python :: 3.9
Classifier: Programming Language :: Python :: 3.10
Classifier: Programming Language :: Python :: 3.11
Requires-Python: >=3.8
License-File: LICENSE
Requires-Dist: numpy>=1.21.0
Requires-Dist: scipy>=1.7.0
Requires-Dist: matplotlib>=3.5.0
Requires-Dist: sounddevice>=0.4.5
Requires-Dist: soundfile>=0.11.0
Provides-Extra: advanced
Requires-Dist: librosa>=0.9.0; extra == "advanced"
Requires-Dist: pygame>=2.1.0; extra == "advanced"
Provides-Extra: dev
Requires-Dist: pytest>=7.0.0; extra == "dev"
Requires-Dist: black>=22.0.0; extra == "dev"
Requires-Dist: flake8>=4.0.0; extra == "dev"
Requires-Dist: mypy>=0.950; extra == "dev"
